niflow/__init__.py
niflow/nipype1/__init__.py
niflow/nipype1/examples/__init__.py
niflow/nipype1/examples/cli.py
niflow/nipype1/examples/dmri_camino_dti.py
niflow/nipype1/examples/dmri_connectivity.py
niflow/nipype1/examples/dmri_connectivity_advanced.py
niflow/nipype1/examples/dmri_dtk_dti.py
niflow/nipype1/examples/dmri_dtk_odf.py
niflow/nipype1/examples/dmri_fsl_dti.py
niflow/nipype1/examples/dmri_group_connectivity_camino.py
niflow/nipype1/examples/dmri_group_connectivity_mrtrix.py
niflow/nipype1/examples/dmri_mrtrix_dti.py
niflow/nipype1/examples/dmri_preprocessing.py
niflow/nipype1/examples/dmri_tbss_nki.py
niflow/nipype1/examples/fmri_ants_openfmri.py
niflow/nipype1/examples/fmri_freesurfer_smooth.py
niflow/nipype1/examples/fmri_fsl.py
niflow/nipype1/examples/fmri_fsl_feeds.py
niflow/nipype1/examples/fmri_fsl_reuse.py
niflow/nipype1/examples/fmri_nipy_glm.py
niflow/nipype1/examples/fmri_openfmri.py
niflow/nipype1/examples/fmri_slicer_coregistration.py
niflow/nipype1/examples/fmri_spm.py
niflow/nipype1/examples/fmri_spm_auditory.py
niflow/nipype1/examples/fmri_spm_dartel.py
niflow/nipype1/examples/fmri_spm_face.py
niflow/nipype1/examples/fmri_spm_nested.py
niflow/nipype1/examples/howto_caching_example.py
niflow/nipype1/examples/rsfmri_vol_surface_preprocessing.py
niflow/nipype1/examples/rsfmri_vol_surface_preprocessing_nipy.py
niflow/nipype1/examples/smri_ants_build_template.py
niflow/nipype1/examples/smri_ants_registration.py
niflow/nipype1/examples/smri_antsregistration_build_template.py
niflow/nipype1/examples/smri_cbs_skullstripping.py
niflow/nipype1/examples/smri_freesurfer.py
niflow/nipype1/examples/smri_fsreconall.py
niflow/nipype1/examples/tessellation_tutorial.py
niflow/nipype1/examples/test_spm.py
niflow/nipype1/examples/workshop_dartmouth_2010.py
niflow_nipype1_examples-0.0.1.dist-info/METADATA
niflow_nipype1_examples-0.0.1.dist-info/WHEEL
niflow_nipype1_examples-0.0.1.dist-info/entry_points.txt
niflow_nipype1_examples-0.0.1.dist-info/top_level.txt
niflow_nipype1_examples-0.0.1.dist-info/RECORD
